BEER_curve/BEER_curve.py
BEER_curve/__init__.py
BEER_curve/utils.py
BEER_curve-0.84.dist-info/LICENSE.txt
BEER_curve-0.84.dist-info/METADATA
BEER_curve-0.84.dist-info/WHEEL
BEER_curve-0.84.dist-info/top_level.txt
BEER_curve-0.84.dist-info/RECORD
